NetEaseMusicDecrypt.cpython-36m-x86_64-linux-gnu.so
NetEaseMusicDecrypt-1.0.dist-info/LICENSE
NetEaseMusicDecrypt-1.0.dist-info/METADATA
NetEaseMusicDecrypt-1.0.dist-info/WHEEL
NetEaseMusicDecrypt-1.0.dist-info/top_level.txt
NetEaseMusicDecrypt-1.0.dist-info/RECORD
