Metadata-Version: 2.1
Name: NetEaseMusicDecrypt
Version: 1.0
Summary: fastest way to covert ncm file
Home-page: https://github.com/rizhiyi/MusicDecoder/
Author: AlphaBrock
Author-email: jcciam@outlook.com
License: MIT License
Keywords: NetEaseMusic,MusicDecoder,MusicDecrypt,MusicCovert
Platform: UNKNOWN
